<?xml version="1.0" encoding="UTF-8"?>
<!-- SKS WS Descriptor File to be used with "WSCreator" -->
<WebService NameSpace="http://xmlns.webpki.org/sksws"
            Service="SKSWS"
            DefaultURL="http://localhost:8080/securekeystore"
            WSDLLocation="META-INF/SKSWS.wsdl"
            Qualified="false"
            xmlns="http://xmlns.webpki.org/wscreator.1.00">

   <LicenseHeader><![CDATA[/*
 *  Copyright 2006-2011 WebPKI.org (http://webpki.org).
 *
 *  Licensed under the Apache License, Version 2.0 (the "License");
 *  you may not use this file except in compliance with the License.
 *  You may obtain a copy of the License at
 *
 *      http://www.apache.org/licenses/LICENSE-2.0
 *
 *  Unless required by applicable law or agreed to in writing, software
 *  distributed under the License is distributed on an "AS IS" BASIS,
 *  WITHOUT WARRANTIES OR CONDITIONS OF ANY KIND, either express or implied.
 *  See the License for the specific language governing permissions and
 *  limitations under the License.
 *
 */
]]></LicenseHeader>
   <JavaServer ClassName="org.MySRV" Imports="org.webpki.sks.Something">
     <ClassHeader><![CDATA[/**
 *  This is the server :-)
 */
]]></ClassHeader>
     <SupportCode><![CDATA[
	   void localMethod (String epub)
	     {
	     }
]]></SupportCode>
   </JavaServer>
   <JavaClient ClassName="org.cli.MyCLI">
     <ClassHeader><![CDATA[/**
 *  This is the client :-)
 */
]]></ClassHeader>
   </JavaClient>
   <Exception ClassName="org.example.Ex5">
     <Property Name="message" Type="string"/>
   </Exception>
   <Exception ClassName="org.blah.Shit" XMLName="XML_Shit">
     <Property Name="baddy" Type="string" List="true" Null="true"/>
     <Property Name="int_y" XMLName="integrat" Type="int"/>
   </Exception>
   <Method Name="kurt">
     <Input Name="glub" Type="string"/>
     <Input Name="bolg" Type="binary" List="true"/>
     <Output Name="kurt" Type="int" Comment="something useful"/>
   </Method>
   <Method Name="kurt2">
     <Input Name="glub" Type="string"/>
     <Input Name="bolg" Type="binary" List="true"/>
     <Output Name="kurt" Type="int"/>
     <Output Name="d_urt" Type="short" XMLName="Durt"/>
   </Method>
   <Method Name="akurt" Throws="Ex5 Shit">
   <Code><![CDATA[
        if (a < b && a < 0) then
          {
            return 1;
          }
        else
          {
            return 0;
          }
]]></Code></Method>
</WebService>
